simple_git_deploy.py
simple_git_deploy-0.6.dist-info/entry_points.txt
simple_git_deploy-0.6.dist-info/LICENSE.txt
simple_git_deploy-0.6.dist-info/WHEEL
simple_git_deploy-0.6.dist-info/METADATA
simple_git_deploy-0.6.dist-info/RECORD
